MANIFEST.in
setup.py
ArchiveTextMiner/__init__.py
ArchiveTextMiner/main.py
ArchiveTextMiner.egg-info/PKG-INFO
ArchiveTextMiner.egg-info/SOURCES.txt
ArchiveTextMiner.egg-info/dependency_links.txt
ArchiveTextMiner.egg-info/entry_points.txt
ArchiveTextMiner.egg-info/requires.txt
ArchiveTextMiner.egg-info/top_level.txt
ArchiveTextMiner/docs/LICENSE.md
ArchiveTextMiner/docs/README.md
ArchiveTextMiner/docs/requirements.txt
ArchiveTextMiner/input/test.zip
ArchiveTextMiner/media/ArchiveTextMiner_favicon.png
ArchiveTextMiner/media/ArchiveTextMiner_logo.png
ArchiveTextMiner/modules/__init__.py
ArchiveTextMiner/modules/text_miner.py